hpp2plantuml/__init__.py
hpp2plantuml/hpp2plantuml.py
hpp2plantuml/templates/default.puml
hpp2plantuml-0.8.5.dist-info/LICENSE
hpp2plantuml-0.8.5.dist-info/METADATA
hpp2plantuml-0.8.5.dist-info/WHEEL
hpp2plantuml-0.8.5.dist-info/entry_points.txt
hpp2plantuml-0.8.5.dist-info/top_level.txt
hpp2plantuml-0.8.5.dist-info/RECORD
