Metadata-Version: 2.1
Name: hpp2plantuml
Version: 0.8.5
Summary: Convert C++ header files to PlantUML
Home-page: https://github.com/thibaultmarin/hpp2plantuml
Author: Thibault Marin
Author-email: thibault.marin@gmx.com
Maintainer: Thibault Marin
Maintainer-email: thibault.marin@gmx.com
License: MIT
Keywords: class
Classifier: Development Status :: 4 - Beta
Classifier: Intended Audience :: Developers
Classifier: Natural Language :: English
Classifier: License :: OSI Approved :: MIT License
Classifier: Operating System :: OS Independent
Classifier: Programming Language :: Python
Classifier: Programming Language :: Python :: 3
Classifier: Programming Language :: Python :: Implementation :: PyPy
Classifier: Topic :: Software Development :: Libraries :: Python Modules
License-File: LICENSE
Requires-Dist: argparse
Requires-Dist: jinja2
Requires-Dist: robotpy-cppheaderparser
Requires-Dist: sphinx
